[
  {
    "key": "minorLeaderCategory:africa",
    "name": "Africa",
    "concept": "conceptType:minorLeader"
  },
  {
    "key": "minorLeaderCategory:america",
    "name": "America",
    "concept": "conceptType:minorLeader"
  },
  {
    "key": "minorLeaderCategory:andea",
    "name": "Andea",
    "concept": "conceptType:minorLeader"
  },
  {
    "key": "minorLeaderCategory:asia",
    "name": "Asia",
    "concept": "conceptType:minorLeader"
  },
  {
    "key": "minorLeaderCategory:europe",
    "name": "Europe",
    "concept": "conceptType:minorLeader"
  },
  {
    "key": "minorLeaderCategory:levantica",
    "name": "Levantica",
    "concept": "conceptType:minorLeader"
  },
  {
    "key": "minorLeaderCategory:mediterra",
    "name": "Mediterra",
    "concept": "conceptType:minorLeader"
  },
  {
    "key": "minorLeaderCategory:oceania",
    "name": "Oceania",
    "concept": "conceptType:minorLeader"
  },
  {
    "key": "minorLeaderCategory:siberia",
    "name": "Siberia",
    "concept": "conceptType:minorLeader"
  },
  {
    "key": "minorLeaderCategory:taiga",
    "name": "Taiga",
    "concept": "conceptType:minorLeader"
  }
]